README.md
setup.cfg
setup.py
eis/__init__.py
eis/gdv/__init__.py
eis/gdv/api_client.py
eis/gdv/configuration.py
eis/gdv/exceptions.py
eis/gdv/model_utils.py
eis/gdv/rest.py
eis/gdv/api/__init__.py
eis/gdv/api/health_api.py
eis/gdv/api/mailbox_api.py
eis/gdv/api/messages_api.py
eis/gdv/api/users_api.py
eis/gdv/api/vbas_api.py
eis/gdv/api/vbus_api.py
eis/gdv/api/zip_codes_api.py
eis/gdv/apis/__init__.py
eis/gdv/model/__init__.py
eis/gdv/model/address_class.py
eis/gdv/model/change_password_request_dto.py
eis/gdv/model/change_password_response_class.py
eis/gdv/model/create_mailbox_request_dto.py
eis/gdv/model/create_user_request_dto.py
eis/gdv/model/create_user_response_class.py
eis/gdv/model/create_vba_request_dto.py
eis/gdv/model/create_vba_response_class.py
eis/gdv/model/create_vbu_request_dto.py
eis/gdv/model/create_vbu_response_class.py
eis/gdv/model/create_vbuv_request_dto.py
eis/gdv/model/create_vbuv_response_class.py
eis/gdv/model/get_request_message_response_class.py
eis/gdv/model/get_response_message_response_class.py
eis/gdv/model/get_user_response_class.py
eis/gdv/model/get_vba_response_class.py
eis/gdv/model/get_vbu_response_class.py
eis/gdv/model/get_zip_code_response_class.py
eis/gdv/model/inline_response200.py
eis/gdv/model/inline_response503.py
eis/gdv/model/list_all_messages_response_class.py
eis/gdv/model/list_requests_messages_response_class.py
eis/gdv/model/list_responses_messages_response_class.py
eis/gdv/model/list_users_response_class.py
eis/gdv/model/list_vbas_response_class.py
eis/gdv/model/list_vbus_response_class.py
eis/gdv/model/list_zip_codes_response_class.py
eis/gdv/model/login_reply_response_class.py
eis/gdv/model/login_request_dto.py
eis/gdv/model/login_response_class.py
eis/gdv/model/message_class.py
eis/gdv/model/request_details_class.py
eis/gdv/model/request_message_class.py
eis/gdv/model/response_details_class.py
eis/gdv/model/response_message_class.py
eis/gdv/model/store_zip_codes_request_dto.py
eis_gdv.egg-info/PKG-INFO
eis_gdv.egg-info/SOURCES.txt
eis_gdv.egg-info/dependency_links.txt
eis_gdv.egg-info/requires.txt
eis_gdv.egg-info/top_level.txt
