Metadata-Version: 2.1
Name: eis-gdv
Version: 2.4.0
Summary: EMIL GdvService
Home-page: UNKNOWN
Author: Contact us
Author-email: kontakt@emil.de
License: UNKNOWN
Keywords: OpenAPI,OpenAPI-Generator,EMIL GdvService
Platform: UNKNOWN
Requires-Python: >=3.6
